{
  "tabPane": [
    {
      "title": "SmartDashboard",
      "autoPopulate": true,
      "autoPopulatePrefix": "SmartDashboard/",
      "widgetPane": {
        "gridSize": 128.0,
        "showGrid": true,
        "hgap": 16.0,
        "vgap": 16.0,
        "titleType": 0,
        "tiles": {
          "6,0": {
            "size": [
              1,
              1
            ],
            "content": {
              "_type": "Text View",
              "_source0": "network_table:///SmartDashboard/VMX Pi Roll (Less Fancy)",
              "_title": "VMX Pi Roll (Less Fancy)",
              "_glyph": 148,
              "_showGlyph": false
            }
          },
          "6,2": {
            "size": [
              1,
              1
            ],
            "content": {
              "_type": "Text View",
              "_source0": "network_table:///SmartDashboard/AutoBalancing PID Loop Output",
              "_title": "AutoBalancing PID Loop Output",
              "_glyph": 148,
              "_showGlyph": false
            }
          },
          "8,2": {
            "size": [
              1,
              2
            ],
            "content": {
              "_type": "PID Controller",
              "_source0": "network_table:///SmartDashboard/AutoBalancing PID",
              "_title": "AutoBalancing PID",
              "_glyph": 148,
              "_showGlyph": false
            }
          },
          "0,0": {
            "size": [
              3,
              3
            ],
            "content": {
              "_type": "Graph",
              "_source0": "network_table:///SmartDashboard/AutoBalancing PID Loop Output",
              "_title": "SmartDashboard/AutoBalancing PID Loop Output",
              "_glyph": 148,
              "_showGlyph": false,
              "Graph/Visible time": 30.0,
              "Graph/X-axis auto scrolling": true,
              "Y-axis/Automatic bounds": true,
              "Y-axis/Upper bound": 1.0,
              "Y-axis/Lower bound": -1.0,
              "Y-axis/Unit": "ul",
              "Visible data/SmartDashboard/AutoBalancing PID Loop Output": true
            }
          },
          "3,0": {
            "size": [
              3,
              3
            ],
            "content": {
              "_type": "Graph",
              "_source0": "network_table:///SmartDashboard/VMX Pi Roll (Less Fancy)",
              "_title": "SmartDashboard/VMX Pi Roll (Less Fancy)",
              "_glyph": 148,
              "_showGlyph": false,
              "Graph/Visible time": 30.0,
              "Graph/X-axis auto scrolling": true,
              "Y-axis/Automatic bounds": true,
              "Y-axis/Upper bound": 1.0,
              "Y-axis/Lower bound": -1.0,
              "Y-axis/Unit": "ul",
              "Visible data/SmartDashboard/VMX Pi Roll (Less Fancy)": true
            }
          },
          "7,0": {
            "size": [
              1,
              1
            ],
            "content": {
              "_type": "Text View",
              "_source0": "network_table:///SmartDashboard/kD",
              "_title": "/SmartDashboard/kD",
              "_glyph": 148,
              "_showGlyph": false
            }
          },
          "7,1": {
            "size": [
              1,
              1
            ],
            "content": {
              "_type": "Text View",
              "_source0": "network_table:///SmartDashboard/kI",
              "_title": "/SmartDashboard/kI",
              "_glyph": 148,
              "_showGlyph": false
            }
          },
          "7,2": {
            "size": [
              1,
              1
            ],
            "content": {
              "_type": "Text View",
              "_source0": "network_table:///SmartDashboard/kP",
              "_title": "/SmartDashboard/kP",
              "_glyph": 148,
              "_showGlyph": false
            }
          }
        }
      }
    },
    {
      "title": "LiveWindow",
      "autoPopulate": true,
      "autoPopulatePrefix": "LiveWindow/",
      "widgetPane": {
        "gridSize": 128.0,
        "showGrid": true,
        "hgap": 16.0,
        "vgap": 16.0,
        "titleType": 0,
        "tiles": {
          "0,0": {
            "size": [
              2,
              1
            ],
            "content": {
              "_type": "Basic Subsystem",
              "_source0": "network_table:///LiveWindow/DriveTrain",
              "_title": "DriveTrain",
              "_glyph": 148,
              "_showGlyph": false
            }
          },
          "2,0": {
            "size": [
              2,
              4
            ],
            "content": {
              "_type": "Subsystem Layout",
              "_source0": "network_table:///LiveWindow/Ungrouped/Scheduler/Ids",
              "_title": "Ungrouped/Scheduler/Ids",
              "_glyph": 149,
              "_showGlyph": false,
              "Layout/Label position": "BOTTOM",
              "_children": []
            }
          },
          "4,0": {
            "size": [
              2,
              4
            ],
            "content": {
              "_type": "Subsystem Layout",
              "_source0": "network_table:///LiveWindow/ExampleSubsystem",
              "_title": "ExampleSubsystem",
              "_glyph": 149,
              "_showGlyph": false,
              "Layout/Label position": "BOTTOM",
              "_children": []
            }
          },
          "6,0": {
            "size": [
              2,
              4
            ],
            "content": {
              "_type": "Subsystem Layout",
              "_source0": "network_table:///LiveWindow/GrabbyArm",
              "_title": "GrabbyArm",
              "_glyph": 149,
              "_showGlyph": false,
              "Layout/Label position": "BOTTOM",
              "_children": []
            }
          },
          "8,0": {
            "size": [
              1,
              1
            ],
            "content": {
              "_type": "Text View",
              "_source0": "network_table:///LiveWindow/Ungrouped/MecanumDrive[1]/Front Left Motor Speed",
              "_title": "Ungrouped/MecanumDrive[1]/Front Left Motor Speed",
              "_glyph": 148,
              "_showGlyph": false
            }
          },
          "0,1": {
            "size": [
              1,
              1
            ],
            "content": {
              "_type": "Text View",
              "_source0": "network_table:///LiveWindow/Ungrouped/MecanumDrive[1]/Front Right Motor Speed",
              "_title": "Ungrouped/MecanumDrive[1]/Front Right Motor Speed",
              "_glyph": 148,
              "_showGlyph": false
            }
          },
          "1,1": {
            "size": [
              1,
              1
            ],
            "content": {
              "_type": "Text View",
              "_source0": "network_table:///LiveWindow/Ungrouped/MecanumDrive[1]/Rear Left Motor Speed",
              "_title": "Ungrouped/MecanumDrive[1]/Rear Left Motor Speed",
              "_glyph": 148,
              "_showGlyph": false
            }
          },
          "8,1": {
            "size": [
              1,
              1
            ],
            "content": {
              "_type": "Text View",
              "_source0": "network_table:///LiveWindow/Ungrouped/MecanumDrive[1]/Rear Right Motor Speed",
              "_title": "Ungrouped/MecanumDrive[1]/Rear Right Motor Speed",
              "_glyph": 148,
              "_showGlyph": false
            }
          },
          "0,2": {
            "size": [
              1,
              1
            ],
            "content": {
              "_type": "Text View",
              "_source0": "network_table:///LiveWindow/Ungrouped/DoubleSolenoid[0,0]/Value",
              "_title": "Ungrouped/DoubleSolenoid[0,0]/Value",
              "_glyph": 148,
              "_showGlyph": false
            }
          },
          "1,2": {
            "size": [
              1,
              1
            ],
            "content": {
              "_type": "Text View",
              "_source0": "network_table:///LiveWindow/Ungrouped/DoubleSolenoid[0,2]/Value",
              "_title": "Ungrouped/DoubleSolenoid[0,2]/Value",
              "_glyph": 148,
              "_showGlyph": false
            }
          },
          "0,3": {
            "size": [
              2,
              1
            ],
            "content": {
              "_type": "Motor Controller",
              "_source0": "network_table:///LiveWindow/Ungrouped/MotorControllerGroup[1]",
              "_title": "Ungrouped/MotorControllerGroup[1]",
              "_glyph": 148,
              "_showGlyph": false,
              "Visuals/Orientation": "HORIZONTAL"
            }
          }
        }
      }
    },
    {
      "title": "LimeLight",
      "autoPopulate": false,
      "autoPopulatePrefix": "",
      "widgetPane": {
        "gridSize": 128.0,
        "showGrid": true,
        "hgap": 16.0,
        "vgap": 16.0,
        "titleType": 0,
        "tiles": {
          "0,0": {
            "size": [
              6,
              4
            ],
            "content": {
              "_type": "Camera Stream",
              "_source0": "camera_server://limelight",
              "_title": "limelight",
              "_glyph": 148,
              "_showGlyph": false,
              "Crosshair/Show crosshair": true,
              "Crosshair/Crosshair color": "#FFFFFFFF",
              "Controls/Show controls": true,
              "Controls/Rotation": "NONE",
              "compression": -1.0,
              "fps": -1,
              "imageWidth": -1,
              "imageHeight": -1
            }
          },
          "8,0": {
            "size": [
              1,
              1
            ],
            "content": {
              "_type": "Text View",
              "_source0": "network_table:///limelight/tx",
              "_title": "limelight/tx",
              "_glyph": 148,
              "_showGlyph": false
            }
          },
          "7,0": {
            "size": [
              1,
              1
            ],
            "content": {
              "_type": "Text View",
              "_source0": "network_table:///limelight/ty",
              "_title": "limelight/ty",
              "_glyph": 148,
              "_showGlyph": false
            }
          }
        }
      }
    },
    {
      "title": "Tab 4",
      "autoPopulate": false,
      "autoPopulatePrefix": "",
      "widgetPane": {
        "gridSize": 128.0,
        "showGrid": true,
        "hgap": 16.0,
        "vgap": 16.0,
        "titleType": 0,
        "tiles": {
          "3,1": {
            "size": [
              1,
              1
            ],
            "content": {
              "_type": "Text View",
              "_source0": "network_table:///SmartDashboard/backLeft/Value",
              "_title": "SmartDashboard/backLeft/Value",
              "_glyph": 148,
              "_showGlyph": false
            }
          },
          "4,1": {
            "size": [
              1,
              1
            ],
            "content": {
              "_type": "Text View",
              "_source0": "network_table:///SmartDashboard/backRight/Value",
              "_title": "SmartDashboard/backRight/Value",
              "_glyph": 148,
              "_showGlyph": false
            }
          },
          "4,0": {
            "size": [
              1,
              1
            ],
            "content": {
              "_type": "Text View",
              "_source0": "network_table:///SmartDashboard/frontRight/Value",
              "_title": "SmartDashboard/frontRight/Value",
              "_glyph": 148,
              "_showGlyph": false
            }
          },
          "3,0": {
            "size": [
              1,
              1
            ],
            "content": {
              "_type": "Text View",
              "_source0": "network_table:///SmartDashboard/frontLeft/Value",
              "_title": "SmartDashboard/frontLeft/Value",
              "_glyph": 148,
              "_showGlyph": false
            }
          },
          "0,0": {
            "size": [
              1,
              1
            ],
            "content": {
              "_type": "Text View",
              "_source0": "network_table:///SmartDashboard/BottomMotor/Value",
              "_title": "SmartDashboard/BottomMotor/Value",
              "_glyph": 148,
              "_showGlyph": false
            }
          },
          "1,0": {
            "size": [
              1,
              1
            ],
            "content": {
              "_type": "Text View",
              "_source0": "network_table:///SmartDashboard/TopMotor/Value",
              "_title": "SmartDashboard/TopMotor/Value",
              "_glyph": 148,
              "_showGlyph": false
            }
          },
          "2,0": {
            "size": [
              1,
              1
            ],
            "content": {
              "_type": "Text View",
              "_source0": "network_table:///SmartDashboard/LeftStick",
              "_title": "SmartDashboard/LeftStick",
              "_glyph": 148,
              "_showGlyph": false
            }
          },
          "6,1": {
            "size": [
              1,
              1
            ],
            "content": {
              "_type": "Text View",
              "_source0": "network_table:///SmartDashboard/armEncoderCounts",
              "_title": "/SmartDashboard/armEncoderCounts",
              "_glyph": 148,
              "_showGlyph": false
            }
          },
          "5,0": {
            "size": [
              2,
              1
            ],
            "content": {
              "_type": "Encoder",
              "_source0": "network_table:///SmartDashboard/armEncoder",
              "_title": "/SmartDashboard/armEncoder",
              "_glyph": 148,
              "_showGlyph": false
            }
          },
          "8,3": {
            "size": [
              1,
              1
            ],
            "content": {
              "_type": "Text View",
              "_source0": "network_table:///SmartDashboard/RightStickX Value",
              "_title": "/SmartDashboard/RightStickX Value",
              "_glyph": 148,
              "_showGlyph": false
            }
          },
          "4,3": {
            "size": [
              1,
              1
            ],
            "content": {
              "_type": "Text View",
              "_source0": "network_table:///SmartDashboard/LeftStickY Value",
              "_title": "/SmartDashboard/LeftStickY Value",
              "_glyph": 148,
              "_showGlyph": false
            }
          },
          "5,3": {
            "size": [
              1,
              1
            ],
            "content": {
              "_type": "Text View",
              "_source0": "network_table:///SmartDashboard/LeftStickX Value",
              "_title": "/SmartDashboard/LeftStickX Value",
              "_glyph": 148,
              "_showGlyph": false
            }
          },
          "7,3": {
            "size": [
              1,
              1
            ],
            "content": {
              "_type": "Text View",
              "_source0": "network_table:///SmartDashboard/RightStickY Value",
              "_title": "/SmartDashboard/RightStickY Value",
              "_glyph": 148,
              "_showGlyph": false
            }
          },
          "4,2": {
            "size": [
              1,
              1
            ],
            "content": {
              "_type": "Text View",
              "_source0": "network_table:///SmartDashboard/X Value",
              "_title": "/SmartDashboard/X Value",
              "_glyph": 148,
              "_showGlyph": false
            }
          },
          "5,2": {
            "size": [
              1,
              1
            ],
            "content": {
              "_type": "Text View",
              "_source0": "network_table:///SmartDashboard/Y Value",
              "_title": "/SmartDashboard/Y Value",
              "_glyph": 148,
              "_showGlyph": false
            }
          },
          "6,2": {
            "size": [
              1,
              1
            ],
            "content": {
              "_type": "Text View",
              "_source0": "network_table:///SmartDashboard/Z Value",
              "_title": "/SmartDashboard/Z Value",
              "_glyph": 148,
              "_showGlyph": false
            }
          }
        }
      }
    }
  ],
  "windowGeometry": {
    "x": -8.0,
    "y": -8.0,
    "width": 1382.0,
    "height": 744.0
  }
}